{
    "character_credits": [
        "Abel",
        "Abnegazar",
        "Abra Kadabra",
        "Adam Strange",
        "Air Wave",
        "Air Wave (Larry Jordan)",
        "Al Pratt",
        "Alan Scott",
        "Alanna Strange",
        "Albert Michaels",
        "Alley-Kat Abra",
        "Amadeus Arkham",
        "Amazing-Man (Will Everett)",
        "Amazo",
        "Ambush Bug",
        "Amethyst",
        "Angle Man",
        "Animal Man",
        "Anthro",
        "Anton Arcane",
        "Aquaman",
        "Arak",
        "Arion",
        "Atomic Knight",
        "Auron",
        "Babe",
        "Barry Allen",
        "Danette Reilly",
        "Darkseid",
        "Dart",
        "Doctor Fate (Kent Nelson)",
        "Floronic Man",
        "Ghast",
        "Guardian",
        "Hal Jordan",
        "Hawkgirl",
        "Hawkman",
        "Hourman (Rex Tyler)",
        "Jean Loring",
        "John Law",
        "Johnny Quick",
        "Joker",
        "Joker",
        "Li-San O''Rourke",
        "Libby Lawrence",
        "Lucas Orion",
        "Lydia Perez",
        "Martian Manhunter",
        "Martin Champion",
        "Martin Hawkins",
        "Mohandas Singh",
        "Morphea",
        "Nikos Aegeus",
        "Pakrat",
        "Plastic Man",
        "Professor Ivo",
        "Rath",
        "Ray Palmer",
        "Robert Crane",
        "Ronal",
        "Sardath",
        "Shining Knight",
        "Storm the Seahorse",
        "Taz",
        "Tempest",
        "Tempest",
        "Tula",
        "Two-Face",
        "Vulko",
        "Winged Victory",
        "Wonder Woman"
    ],
    "cover_date": "1985-03-31",
    "description": "WHO\u2019S WHO is a meticulously detailed, alphabetically arranged series of reference volumes that provides personal data, history and powers and weapons for countless DC characters, both popular and obscure, both new (circa the mid-1980s) and old. Volume One has entries for Adam Strange, Amazo, Animal Man, Aquaman and many others. Character renderings are by such artistic greats as Gil Kane, George P\u00e9rez, Joe Orlando, Carmine Infantino, Jerry Ordway, Dick Giordano and Marshall Rogers.The Definitive Directory of the DC Universe containing profiles on characters listed from Abel to Auron.",
    "image": "https://comicvine1.cbsistatic.com/uploads/scale_medium/0/574/92740-18197-106579-1-whos-who-the-defin.jpg",
    "name": "Abel to Auron",
    "person_credits": [
        "Alex Saviuk:penciler",
        "Anthony Tollin:colorist",
        "Bob Oksner:inker",
        "Carmine Infantino:penciler",
        "Chuck Patton:penciler",
        "Craig Hamilton:penciler",
        "Curt Swan:penciler",
        "Dick Giordano:inker",
        "Don Heck:penciler",
        "Eduardo Barreto:penciler, inker",
        "Ernie Colon:penciler, inker",
        "Frank McLaughlin:inker",
        "George P\u00e9rez:penciler",
        "Gil Kane:penciler, inker",
        "Greg Theakston:penciler",
        "Howard Post:penciler",
        "Jan Duursema-Mandrake:penciler, inker",
        "Jerry Ordway:penciler",
        "Joe Orlando:penciler",
        "John Beatty:inker",
        "John Totleben:inker",
        "Keith Giffen:penciler",
        "Len Wein:editor",
        "Marshall Rogers:penciler",
        "Marv Wolfman:writer",
        "Mike Zeck:penciler",
        "Rick Hoberg:penciler",
        "Rick Magyar:inker",
        "Romeo Tanghal:inker",
        "Scott Shaw:penciler",
        "Steve Bissette:penciler",
        "Tatjana Wood:colorist, cover",
        "Tod Smith:penciler",
        "Typeset:letterer"
    ],
    "series": "Who''s Who: The Definitive Directory of the DC Universe"
}