{
    "character_credits": [
        "Angel",
        "Beast",
        "Cyclops",
        "Iceman",
        "Jean Grey",
        "Magneto",
        "Professor X"
    ],
    "cover_date": "1963-09-01",
    "description": "Will the X-Men fight to see another day? And how does IceMan fit into all this? Find out in the first ever appearance of the mutant team!",
    "image": "https://comicvine1.cbsistatic.com/uploads/scale_medium/0/5344/1355017-uxm_v1_001_01.jpg",
    "name": "X-Men",
    "person_credits": [
        "Jack Kirby:penciler",
        "Paul Reinman:inker",
        "Sam Rosen:letterer",
        "Stan Lee:writer"
    ],
    "series": "The X-Men"
}