{
    "character_credits": [
        "Black Bolt",
        "Black Panther",
        "Crystal",
        "Gorgon",
        "Human Torch",
        "Invisible Woman",
        "Karnak",
        "Maximus",
        "Medusa",
        "Mr. Fantastic",
        "Thing",
        "Wyatt Wingfoot"
    ],
    "cover_date": "1966-07-01",
    "description": "The first appearance of Black Panther! On a mission in the remote wilderness of Wakanda, the Fantastic Four encounter one of Marvel\u2019s most iconic heroes. But how are the Inhumans involved in this earthly encounter? The FF bested in battle by the Black Panther!In the jungles of Africa the Fantastic Four are called by the king of the Wakandas, only to test the power of the Black Panther.This is the first appearance of the Black Panther.",
    "image": "https://comicvine1.cbsistatic.com/uploads/scale_medium/0/4/7851-2045-8666-1-fantastic-four.jpg",
    "name": "Introducing the Sensational Black Panther",
    "person_credits": [
        "Jack Kirby:penciler, cover",
        "Joe Sinnott:inker, cover",
        "Sam Rosen:letterer",
        "Stan Lee:writer, editor, cover"
    ],
    "series": "Fantastic Four"
}