{
    "character_credits": [
        "Amazing Fantasy Boy",
        "Aunt May",
        "Baxter Bigelow ",
        "Bernard OBrien",
        "Chet Huntley",
        "Crusher Hogan",
        "Dr. Eric Schwinner",
        "Flash Thompson",
        "Jason Ionello",
        "Liz Allan",
        "Maxie Shiffman",
        "Old Pedros",
        "Raymond Warren",
        "Rocco Rank",
        "Sally Avril",
        "Seymour OReilly",
        "Spider-Man",
        "The Burglar",
        "Uncle Ben"
    ],
    "cover_date": "1962-08-31",
    "description": "Plot SummariesSpider-Man!Peter Parker is but a lonely high-school student until one day whilst he attends a science experiment during which a spider absorbs an uncanny amount of radiation before biting him. Soon after Peter discovers that he has gained powers similar to that of a spider \u2013 he is incredibly strong, can stick to walls and now has increased senses. Deciding to use his newfound powers to earn some money he creates the identity of \u2018Spider-Man\u2019 for himself and soon becomes an overnight sensation. With his new found fame and success Peter becomes much more selfish and fails to stop a fleeing criminal claiming from now on he only looks out for himself and his Aunt and Uncle.However upon returning to his house one night Peter discovers that his beloved Uncle Ben has been shot in a botched robbery. As Spider-Man, Peter tracks down the murderer but is shocked to discover that it is the thief he allowed to escape earlier. Racked with the guilt of his Uncles death Peter realises th",
    "image": "https://comicvine1.cbsistatic.com/uploads/scale_medium/11/117763/2431998-amazingfantasy15.jpg",
    "name": "Spider-Man! / The Bell Ringer / The Man in the Mummy Case / There are Martians Among Us",
    "person_credits": [
        "Andy Yanchus:colorist",
        "Artie Simek:letterer",
        "Jack Kirby:artist, cover",
        "Stan Lee:writer, editor",
        "Steve Ditko:writer, artist, penciler, inker"
    ],
    "series": "Amazing Fantasy"
}